{
  "header": {
    "id": "certifi",
    "version": "2020.6.20",
    "type": "native",
    "build_requires": []
  },
  "module": {
    "name": "certifi",
    "buildsystem": "simple",
    "build-commands": [
      "python3 setup.py install --prefix=/app --root=/"
    ],
    "sources": [
      {
        "type": "archive",
        "url": "https://files.pythonhosted.org/packages/40/a7/ded59fa294b85ca206082306bba75469a38ea1c7d44ea7e1d64f5443d67a/certifi-2020.6.20.tar.gz",
        "sha256": "5930595817496dd21bb8dc35dad090f1c2cd0adfaf21204bf6732ca5d8ee34d3"
      }
    ]
  }
}
