{
  "header": {
    "id": "libgedit-tepl",
    "version": "unknown",
    "type": "native",
    "build_requires": []
  },
  "module": {
    "name": "libgedit-tepl",
    "buildsystem": "meson",
    "config-opts": [
      "-Dgtk_doc=false",
      "-Dtests=false"
    ],
    "sources": [
      {
        "type": "git",
        "url": "https://gitlab.gnome.org/World/gedit/libgedit-tepl.git",
        "tag": "6.14.0",
        "commit": "d60f7ded17b52ea42091c073ea81090e91f38620",
        "x-checker-data": {
          "type": "git",
          "tag-pattern": "^6\\.14\\.\\d+$"
        }
      }
    ]
  }
}
