{
  "header": {
    "id": "nuget-sources",
    "version": "10.0.8",
    "type": "native",
    "build_requires": []
  },
  "module": {
    "name": "nuget-sources",
    "buildsystem": "simple",
    "build-commands": [
      "mkdir -p /usr/lib/sdk/dotnet10/nuget/packages",
      "cp * /usr/lib/sdk/dotnet10/nuget/packages"
    ],
    "sources": [
      {
        "type": "file",
        "only-arches": [
          "x86_64"
        ],
        "url": "https://api.nuget.org/v3-flatcontainer/microsoft.aspnetcore.app.runtime.linux-x64/10.0.8/microsoft.aspnetcore.app.runtime.linux-x64.10.0.8.nupkg",
        "sha512": "a781e31a112160fdc0ec19b861661459baccb19209c2be4cce9acd911898b36de7308dc054da164a4bcf03a1db54572360b1d135c7d54f590fc1fad0c9ef01bc",
        "x-checker-data": {
          "type": "html",
          "url": "https://dotnetcli.blob.core.windows.net/dotnet/aspnetcore/Runtime/10.0/latest.version",
          "version-pattern": "^([\\d\\.a-z-]+)$",
          "url-template": "https://api.nuget.org/v3-flatcontainer/microsoft.aspnetcore.app.runtime.linux-x64/$version/microsoft.aspnetcore.app.runtime.linux-x64.$version.nupkg"
        }
      },
      {
        "type": "file",
        "only-arches": [
          "x86_64"
        ],
        "url": "https://api.nuget.org/v3-flatcontainer/microsoft.netcore.app.runtime.linux-x64/10.0.8/microsoft.netcore.app.runtime.linux-x64.10.0.8.nupkg",
        "sha512": "0c06ed751c8c0a4bb91fcb0ed2b57b171f8ae3d2d7ce592675c9a2e56703fed6b39e5f4e11c1ca2f2d795972404246f1e7b89b6c9df903c0fcd34b0e021beac1",
        "x-checker-data": {
          "type": "html",
          "url": "https://dotnetcli.blob.core.windows.net/dotnet/aspnetcore/Runtime/10.0/latest.version",
          "version-pattern": "^([\\d\\.a-z-]+)$",
          "url-template": "https://api.nuget.org/v3-flatcontainer/microsoft.netcore.app.runtime.linux-x64/$version/microsoft.netcore.app.runtime.linux-x64.$version.nupkg"
        }
      },
      {
        "type": "file",
        "only-arches": [
          "x86_64"
        ],
        "url": "https://api.nuget.org/v3-flatcontainer/microsoft.netcore.app.crossgen2.linux-x64/10.0.8/microsoft.netcore.app.crossgen2.linux-x64.10.0.8.nupkg",
        "sha512": "4e7f439f306c864ea01e9fcf3dee441fe80608e3352e3254617412217cebd8823d9399bc243494f2735d53425a3f16dcdff7bdd7fcda902755e2801feaa7f03c",
        "x-checker-data": {
          "type": "html",
          "url": "https://dotnetcli.blob.core.windows.net/dotnet/aspnetcore/Runtime/10.0/latest.version",
          "version-pattern": "^([\\d\\.a-z-]+)$",
          "url-template": "https://api.nuget.org/v3-flatcontainer/microsoft.netcore.app.crossgen2.linux-x64/$version/microsoft.netcore.app.crossgen2.linux-x64.$version.nupkg"
        }
      },
      {
        "type": "file",
        "only-arches": [
          "aarch64"
        ],
        "url": "https://api.nuget.org/v3-flatcontainer/microsoft.aspnetcore.app.runtime.linux-arm64/10.0.8/microsoft.aspnetcore.app.runtime.linux-arm64.10.0.8.nupkg",
        "sha512": "8738142697bca8cad38cb023abe633bb36fec73624647763d5d13843f94c2f5f8b50d9d9106fec2ac678fcace777da12af0225337e6f8d0617e19048d5d45a83",
        "x-checker-data": {
          "type": "html",
          "url": "https://dotnetcli.blob.core.windows.net/dotnet/aspnetcore/Runtime/10.0/latest.version",
          "version-pattern": "^([\\d\\.a-z-]+)$",
          "url-template": "https://api.nuget.org/v3-flatcontainer/microsoft.aspnetcore.app.runtime.linux-arm64/$version/microsoft.aspnetcore.app.runtime.linux-arm64.$version.nupkg"
        }
      },
      {
        "type": "file",
        "only-arches": [
          "aarch64"
        ],
        "url": "https://api.nuget.org/v3-flatcontainer/microsoft.netcore.app.runtime.linux-arm64/10.0.8/microsoft.netcore.app.runtime.linux-arm64.10.0.8.nupkg",
        "sha512": "c8789ed7bd9394a7a284ad7d6405995edbb4d75cf111376b907687cf33383bb979b20b8cce778b573e15cddc3a694f17692f732da2652f4399f6825dcf83019e",
        "x-checker-data": {
          "type": "html",
          "url": "https://dotnetcli.blob.core.windows.net/dotnet/aspnetcore/Runtime/10.0/latest.version",
          "version-pattern": "^([\\d\\.a-z-]+)$",
          "url-template": "https://api.nuget.org/v3-flatcontainer/microsoft.netcore.app.runtime.linux-arm64/$version/microsoft.netcore.app.runtime.linux-arm64.$version.nupkg"
        }
      },
      {
        "type": "file",
        "only-arches": [
          "aarch64"
        ],
        "url": "https://api.nuget.org/v3-flatcontainer/microsoft.netcore.app.crossgen2.linux-arm64/10.0.8/microsoft.netcore.app.crossgen2.linux-arm64.10.0.8.nupkg",
        "sha512": "c336e77b1d1aef5638b866b442882068a29ee666613b1c3c6b5701322a468be02af5c821dee3dae38e9a146b68c5f07fbe43e8484059223baf5e8211ddfb5838",
        "x-checker-data": {
          "type": "html",
          "url": "https://dotnetcli.blob.core.windows.net/dotnet/aspnetcore/Runtime/10.0/latest.version",
          "version-pattern": "^([\\d\\.a-z-]+)$",
          "url-template": "https://api.nuget.org/v3-flatcontainer/microsoft.netcore.app.crossgen2.linux-arm64/$version/microsoft.netcore.app.crossgen2.linux-arm64.$version.nupkg"
        }
      },
      {
        "type": "file",
        "url": "https://api.nuget.org/v3-flatcontainer/microsoft.net.illink.tasks/10.0.8/microsoft.net.illink.tasks.10.0.8.nupkg",
        "sha512": "c8db916c8807ba5418fce8d73062bd50d5b5e4c67e81e0c3e09e2cfdd8edd3773950839d7fc2c3b710618ca4b770e1e5f4f1aa9be1b53fccee9c16d1b440ce7d",
        "x-checker-data": {
          "type": "html",
          "url": "https://dotnetcli.blob.core.windows.net/dotnet/aspnetcore/Runtime/10.0/latest.version",
          "version-pattern": "^([\\d\\.a-z-]+)$",
          "url-template": "https://api.nuget.org/v3-flatcontainer/microsoft.net.illink.tasks/$version/microsoft.net.illink.tasks.$version.nupkg"
        }
      }
    ]
  }
}
