{
  "header": {
    "id": "pcsx2",
    "version": "unknown",
    "type": "native",
    "build_requires": []
  },
  "module": {
    "name": "pcsx2",
    "buildsystem": "cmake-ninja",
    "builddir": true,
    "config-opts": [
      "-DCMAKE_BUILD_TYPE=Release",
      "-DQT_BUILD=ON",
      "-DCUBEB_API=ON",
      "-DX11_API=ON",
      "-DWAYLAND_API=ON",
      "-DENABLE_SETCAP=OFF",
      "-DUSE_SYSTEM_SDL2=ON",
      "-DUSE_SYSTEM_ZSTD=OFF",
      "-DDISABLE_ADVANCE_SIMD=TRUE",
      "-DCMAKE_INTERPROCEDURAL_OPTIMIZATION=ON",
      "-DCMAKE_C_COMPILER=/usr/lib/sdk/llvm16/bin/clang",
      "-DCMAKE_CXX_COMPILER=/usr/lib/sdk/llvm16/bin/clang++",
      "-DCMAKE_EXE_LINKER_FLAGS_INIT=-fuse-ld=/usr/lib/sdk/llvm16/bin/ld.lld",
      "-DCMAKE_MODULE_LINKER_FLAGS_INIT=-fuse-ld=/usr/lib/sdk/llvm16/bin/ld.lld",
      "-DCMAKE_SHARED_LINKER_FLAGS_INIT=-fuse-ld=/usr/lib/sdk/llvm16/bin/ld.lld"
    ],
    "cleanup": [
      "/share/pixmaps",
      "/share/man",
      "/share/doc"
    ],
    "post-install": [
      "cp -r bin/pcsx2-qt ../bin/* ${FLATPAK_DEST}/bin",
      "rm ${FLATPAK_DEST}/bin/portable.ini",
      "install -Dm644 ../bin/resources/icons/AppIconLarge.png ${FLATPAK_DEST}/share/icons/hicolor/256x256/apps/net.pcsx2.PCSX2.png",
      "install -Dm644 ../net.pcsx2.PCSX2.metainfo.xml ${FLATPAK_DEST}/share/metainfo/net.pcsx2.PCSX2.metainfo.xml",
      "install -Dm644 ../.github/workflows/scripts/linux/pcsx2-qt.desktop ${FLATPAK_DEST}/share/applications/net.pcsx2.PCSX2.desktop",
      "desktop-file-edit --set-key=Icon --set-value=net.pcsx2.PCSX2 ${FLATPAK_DEST}/share/applications/net.pcsx2.PCSX2.desktop"
    ],
    "sources": [
      {
        "type": "git",
        "url": "https://github.com/PCSX2/pcsx2.git",
        "tag": "v1.7.4666",
        "commit": "d38ad1df94a073f2891992cd47b80ed3418fc3bc",
        "x-checker-data": {
          "type": "git",
          "tag-pattern": "^v([\\d.]+)$"
        }
      },
      {
        "type": "file",
        "path": "net.pcsx2.PCSX2.metainfo.xml"
      }
    ]
  }
}
