{
  "header": {
    "id": "protobuf",
    "version": "3.17.3",
    "type": "native",
    "build_requires": []
  },
  "module": {
    "name": "protobuf",
    "buildsystem": "autotools",
    "config-opts": [
      "DIST_LANG=cpp"
    ],
    "cleanup": [
      "/bin/protoc*",
      "/lib/libprotoc*",
      "/lib/libprotobuf-lite*"
    ],
    "sources": [
      {
        "type": "archive",
        "url": "https://github.com/protocolbuffers/protobuf/releases/download/v3.17.3/protobuf-all-3.17.3.tar.gz",
        "sha256": "77ad26d3f65222fd96ccc18b055632b0bfedf295cb748b712a98ba1ac0b704b2"
      }
    ]
  }
}
