{
  "header": {
    "id": "serf",
    "version": "1.3.10",
    "type": "native",
    "build_requires": []
  },
  "module": {
    "name": "serf",
    "buildsystem": "simple",
    "build-commands": [
      "scons PREFIX=${FLATPAK_DEST} APR=/app/bin/apr-1-config APU=/app/bin/apu-1-config",
      "scons install prefix=${FLATPAK_DEST}"
    ],
    "sources": [
      {
        "type": "archive",
        "url": "https://downloads.apache.org/serf/serf-1.3.10.tar.bz2",
        "sha256": "be81ef08baa2516ecda76a77adf7def7bc3227eeb578b9a33b45f7b41dc064e6",
        "x-checker-data": {
          "type": "html",
          "url": "https://downloads.apache.org/serf/",
          "pattern": "(serf-([\\d.]+).tar.bz2)"
        }
      }
    ]
  }
}
