{
  "header": {
    "id": "vcdimager",
    "version": "2.0.1",
    "type": "native",
    "build_requires": []
  },
  "module": {
    "name": "vcdimager",
    "config-opts": [
      "--disable-static"
    ],
    "sources": [
      {
        "type": "archive",
        "url": "https://ftp.gnu.org/gnu/vcdimager/vcdimager-2.0.1.tar.gz",
        "sha512": "55a9d235149a35fe26576703c623a2c9a3f7deedd2e42e01271fdf1e1fdf14c51ee040ee3b5d15fe1b5860fbd4cbeb437362b1a1f40187c8d4d691b6b89a2230",
        "x-checker-data": {
          "type": "anitya",
          "project-id": 16033,
          "url-template": "https://ftp.gnu.org/gnu/vcdimager/vcdimager-$version.tar.gz"
        }
      },
      {
        "type": "patch",
        "path": "patch/vcdimager-libxml-2.14.patch"
      }
    ],
    "modules": [
      {
        "name": "popt",
        "config-opts": [
          "--disable-static"
        ],
        "sources": [
          {
            "type": "archive",
            "url": "https://ftp.osuosl.org/pub/rpm/popt/releases/popt-1.x/popt-1.19.tar.gz",
            "sha512": "5d1b6a15337e4cd5991817c1957f97fc4ed98659870017c08f26f754e34add31d639d55ee77ca31f29bb631c0b53368c1893bd96cf76422d257f7997a11f6466"
          }
        ]
      }
    ]
  }
}
