{
  "header": {
    "id": "vkd3d-d3d12-32bit",
    "version": "unknown",
    "type": "native",
    "build_requires": []
  },
  "module": {
    "name": "vkd3d-d3d12-32bit",
    "subdir": "vkd3d",
    "only-arches": [
      "x86_64"
    ],
    "build-options": {
      "arch": {
        "x86_64": {
          "ldflags": "-L/app/share/steam/compatibilitytools.d/Proton-Exp/lib32 -L/app/lib32",
          "prepend-path": "/app/share/steam/compatibilitytools.d/Proton-Exp/bin32",
          "append-path": "/usr/lib/sdk/toolchain-i386/bin",
          "env": {
            "CC": "ccache i686-unknown-linux-gnu-gcc",
            "CXX": "ccache i686-unknown-linux-gnu-g++",
            "PKG_CONFIG_PATH": "/app/share/steam/compatibilitytools.d/Proton-Exp/lib32/pkgconfig:/app/lib32/pkgconfig:/app/share/pkgconfig:/usr/lib/i386-linux-gnu/pkgconfig:/usr/share/pkgconfig",
            "LD_RUN_PATH": "/app/share/steam/compatibilitytools.d/Proton-Exp/lib32",
            "FLATPAK_LIBDIR": "/app/share/steam/compatibilitytools.d/Proton-Exp/lib32",
            "FLATPAK_LIBDIR_WINE": "/app/share/steam/compatibilitytools.d/Proton-Exp/lib32/wine",
            "FLATPAK_LIBDIR_WINE_ELF": "/app/share/steam/compatibilitytools.d/Proton-Exp/lib32/wine/i386-unix",
            "FLATPAK_LIBDIR_WINE_PE": "/app/share/steam/compatibilitytools.d/Proton-Exp/lib32/wine/i386-windows"
          },
          "libdir": "/app/share/steam/compatibilitytools.d/Proton-Exp/lib32"
        }
      },
      "env": {
        "WIDL": "i686-w64-mingw32-widl"
      }
    },
    "config-opts": [
      "--disable-doxygen-doc",
      "--disable-tests",
      "--disable-demos",
      "--without-ncurses"
    ],
    "sources": [
      {
        "type": "git",
        "url": "https://github.com/ValveSoftware/Proton.git",
        "tag": "experimental-7.0-20230227",
        "commit": "828bc5ccabcf363b62837448b59a866cc4e78002",
        "x-checker-data": {
          "type": "git",
          "tag-pattern": "^experimental-([\\d\\.-]+\\w?)$",
          "is-main-source": true,
          "source-id": "proton-git-0"
        }
      }
    ]
  }
}
