{
  "header": {
    "id": "yt-dlp",
    "version": "2026.03.17",
    "type": "native",
    "build_requires": []
  },
  "module": {
    "name": "yt-dlp",
    "no-autogen": true,
    "no-make-install": true,
    "make-args": [
      "yt-dlp",
      "PYTHON=/usr/bin/python3"
    ],
    "post-install": [
      "install yt-dlp /app/bin"
    ],
    "sources": [
      {
        "type": "archive",
        "url": "https://github.com/yt-dlp/yt-dlp/releases/download/2026.03.17/yt-dlp.tar.gz",
        "sha512": "ee49a7d929f2dcbd7b2a8ec21696efd135fbdadd88161232363f7a5a2f31e8450bdd24a674b21c5895e21971e3e2382c4b6a4b9b0efc2060a55c5eb7c02f9b93",
        "x-checker-data": {
          "type": "json",
          "url": "https://api.github.com/repos/yt-dlp/yt-dlp/tags",
          "version-query": "[.[].name | select(. != \"nightly\")] | sort[-1]",
          "url-query": "\"https://github.com/yt-dlp/yt-dlp/releases/download/\" + $version + \"/yt-dlp.tar.gz\""
        }
      }
    ]
  }
}
